surjectors/__init__.py
surjectors/util.py
surjectors/_src/__init__.py
surjectors/_src/_transform.py
surjectors/_src/bijectors/__init__.py
surjectors/_src/bijectors/affine_masked_autoregressive.py
surjectors/_src/bijectors/affine_masked_autoregressive_test.py
surjectors/_src/bijectors/affine_masked_coupling.py
surjectors/_src/bijectors/affine_masked_coupling_test.py
surjectors/_src/bijectors/bijector.py
surjectors/_src/bijectors/lu_linear.py
surjectors/_src/bijectors/masked_autoregressive.py
surjectors/_src/bijectors/masked_autoregressive_test.py
surjectors/_src/bijectors/masked_coupling.py
surjectors/_src/bijectors/masked_coupling_test.py
surjectors/_src/bijectors/permutation.py
surjectors/_src/bijectors/rq_masked_coupling.py
surjectors/_src/bijectors/rq_masked_coupling_test.py
surjectors/_src/conditioners/__init__.py
surjectors/_src/conditioners/mlp.py
surjectors/_src/conditioners/transformer.py
surjectors/_src/conditioners/nn/__init__.py
surjectors/_src/conditioners/nn/made.py
surjectors/_src/conditioners/nn/made_test.py
surjectors/_src/conditioners/nn/masked_linear.py
surjectors/_src/distributions/__init__.py
surjectors/_src/distributions/transformed_distribution.py
surjectors/_src/surjectors/__init__.py
surjectors/_src/surjectors/affine_masked_autoregressive_inference_funnel.py
surjectors/_src/surjectors/affine_masked_autoregressive_inference_funnel_test.py
surjectors/_src/surjectors/affine_masked_coupling_generative_funnel.py
surjectors/_src/surjectors/affine_masked_coupling_inference_funnel.py
surjectors/_src/surjectors/affine_masked_coupling_inference_funnel_test.py
surjectors/_src/surjectors/augment.py
surjectors/_src/surjectors/chain.py
surjectors/_src/surjectors/masked_autoregressive_inference_funnel.py
surjectors/_src/surjectors/masked_coupling_inference_funnel.py
surjectors/_src/surjectors/mlp.py
surjectors/_src/surjectors/rq_masked_autoregressive_inference_funnel.py
surjectors/_src/surjectors/rq_masked_coupling_inference_funnel.py
surjectors-0.3.3.dist-info/METADATA
surjectors-0.3.3.dist-info/WHEEL
surjectors-0.3.3.dist-info/licenses/LICENSE
surjectors-0.3.3.dist-info/RECORD
