Metadata-Version: 2.3
Name: surjectors
Version: 0.3.3
Summary: Surjection layers for density estimation with normalizing flows
Project-URL: homepage, https://github.com/dirmeier/surjectors
Author-email: Simon Dirmeier <sfyrbnd@pm.me>
License-Expression: Apache-2.0
License-File: LICENSE
Keywords: density estimation,normalizing flows,surjections
Classifier: Development Status :: 3 - Alpha
Classifier: Intended Audience :: Science/Research
Classifier: License :: OSI Approved :: Apache Software License
Classifier: Programming Language :: Python :: 3
Classifier: Programming Language :: Python :: 3.9
Classifier: Programming Language :: Python :: 3.10
Classifier: Programming Language :: Python :: 3.11
Requires-Python: >=3.9
Requires-Dist: distrax>=0.1.4
Requires-Dist: dm-haiku>=0.0.10
Requires-Dist: jax>=0.4.18
Requires-Dist: jaxlib>=0.4.18
Requires-Dist: optax>=0.1.7
